webapp3/__init__.py
webapp3/main.py
webapp3_flask-0.1.9.dist-info/LICENSE
webapp3_flask-0.1.9.dist-info/METADATA
webapp3_flask-0.1.9.dist-info/WHEEL
webapp3_flask-0.1.9.dist-info/top_level.txt
webapp3_flask-0.1.9.dist-info/RECORD
